wintergreen/__init__.py
wintergreen/assets/aws_root_ca.pem
wintergreen/cli.py
wintergreen/constants.py
wintergreen/crypto/__init__.py
wintergreen/crypto/cert_gen.py
wintergreen/crypto/data_structures.py
wintergreen/initialize/__init__.py
wintergreen/initialize/initialize.py
wintergreen/persistence/__init__.py
wintergreen/persistence/persistence.py
wintergreen/platforms/__init__.py
wintergreen/platforms/aws_iot.py
wintergreen/platforms/base.py
wintergreen/platforms/jitp_role.py
wintergreen/platforms/local.py
wintergreen/provision/__init__.py
wintergreen/provision/provision.py
wintergreen/templates/policy.json
wintergreen/templates/provisioning.json
wintergreen-0.2.2.dist-info/entry_points.txt
wintergreen-0.2.2.dist-info/LICENSE
wintergreen-0.2.2.dist-info/WHEEL
wintergreen-0.2.2.dist-info/METADATA
wintergreen-0.2.2.dist-info/RECORD
