Metadata-Version: 2.1
Name: wintergreen
Version: 0.2.2
Summary: A tool for dealing with AWS IoT certificates
Home-page: https://github.com/verypossible/wintergreen
License: MIT
Keywords: certs,openssl,aws,iot,device,provisioning
Author: Dan Lindeman
Author-email: lindemda@gmail.com
Requires-Python: >=3.7,<4.0
Classifier: License :: OSI Approved :: MIT License
Classifier: Programming Language :: Python :: 3
Classifier: Programming Language :: Python :: 3.7
Classifier: Programming Language :: Python :: 3.8
Requires-Dist: AWSIoTPythonSDK (>=1.4,<2.0)
Requires-Dist: boto3 (>=1.9,<2.0)
Requires-Dist: click (>=7.0,<8.0)
Requires-Dist: cryptography (>=2.6,<3.0)
Project-URL: Repository, https://github.com/verypossible/wintergreen
